setup.py
triangular_arbitrage/__init__.py
triangular_arbitrage/triangular_arbitrage.py
triangular_arbitrage.egg-info/PKG-INFO
triangular_arbitrage.egg-info/SOURCES.txt
triangular_arbitrage.egg-info/dependency_links.txt
triangular_arbitrage.egg-info/top_level.txt