Metadata-Version: 1.0
Name: triangular-arbitrage
Version: 0.0.4
Summary: block chain triangular arbitrage
Home-page: http://github.com/mervynlh/triangular_arbitrage
Author: mervynlh
Author-email: mervyn_lh@163.com
License: MIT
Keywords: block chain triangular arbitrage
Platform: UNKNOWN
